aisert/__init__.py
aisert/aisert.py
aisert/exception.py
aisert/config/__init__.py
aisert/config/config.py
aisert/config/defaults.py
aisert/models/__init__.py
aisert/models/report.py
aisert/models/result.py
aisert/models/validator_enums.py
aisert/utils/print_util.py
aisert/validators/__init__.py
aisert/validators/contains_validator.py
aisert/validators/not_contains_validator.py
aisert/validators/schema_validator.py
aisert/validators/validator.py
aisert/validators/semantic_validator/__init__.py
aisert/validators/semantic_validator/common_semantic_validators.py
aisert/validators/semantic_validator/semantic_validator.py
aisert/validators/semantic_validator/semantic_validator_base.py
aisert/validators/semantic_validator/semantic_validator_factory.py
aisert/validators/token_validator/__init__.py
aisert/validators/token_validator/common_token_validators.py
aisert/validators/token_validator/token_validator.py
aisert/validators/token_validator/token_validator_base.py
aisert/validators/token_validator/token_validator_factory.py
aisert-0.2.0.dist-info/licenses/LICENSE.md
examples/01_configuration_examples.py
examples/02_usage_patterns.py
examples/03_production_use_cases.py
examples/__init__.py
examples/custom_validators_example.py
aisert-0.2.0.dist-info/METADATA
aisert-0.2.0.dist-info/WHEEL
aisert-0.2.0.dist-info/top_level.txt
aisert-0.2.0.dist-info/RECORD
