Metadata-Version: 2.4
Name: aisert
Version: 0.2.0
Summary: Assert-style validation library for AI outputs - ensure your LLMs behave exactly as expected
Author-email: haipad <hariprayush@gmail.com>
License: MIT
Project-URL: Homepage, https://github.com/haipad/aisert
Project-URL: Issues, https://github.com/haipad/aisert/issues
Classifier: Development Status :: 3 - Alpha
Classifier: Intended Audience :: Developers
Classifier: License :: OSI Approved :: MIT License
Classifier: Programming Language :: Python :: 3
Classifier: Programming Language :: Python :: 3.9
Classifier: Programming Language :: Python :: 3.10
Classifier: Programming Language :: Python :: 3.11
Classifier: Programming Language :: Python :: 3.12
Classifier: Topic :: Software Development :: Testing
Classifier: Topic :: Scientific/Engineering :: Artificial Intelligence
Classifier: Operating System :: OS Independent
Requires-Python: >=3.9
License-File: LICENSE.md
Requires-Dist: jsonschema>=4.0.0
Requires-Dist: tiktoken>=0.5.0
Requires-Dist: anthropic>=0.3.0
Requires-Dist: pydantic>=2.0.0
Provides-Extra: sentence-transformers
Requires-Dist: sentence-transformers>=2.0.0; extra == "sentence-transformers"
Requires-Dist: torch>=1.9.0; extra == "sentence-transformers"
Provides-Extra: huggingface
Requires-Dist: transformers>=4.0.0; extra == "huggingface"
Requires-Dist: huggingface_hub>=0.16.0; extra == "huggingface"
Requires-Dist: torch>=1.9.0; extra == "huggingface"
Provides-Extra: all
Requires-Dist: sentence-transformers>=2.0.0; extra == "all"
Requires-Dist: transformers>=4.0.0; extra == "all"
Requires-Dist: huggingface_hub>=0.16.0; extra == "all"
Requires-Dist: torch>=1.9.0; extra == "all"
Dynamic: license-file
